heuristictree/__init__.py
heuristictree/cli.py
heuristictree/parser.py
heuristictree/quick_tree.py
heuristictree/tree.py
heuristictree-1.0.3.dist-info/LICENSE
heuristictree-1.0.3.dist-info/METADATA
heuristictree-1.0.3.dist-info/WHEEL
heuristictree-1.0.3.dist-info/entry_points.txt
heuristictree-1.0.3.dist-info/RECORD
