Metadata-Version: 2.1
Name: heuristictree
Version: 1.0.3
Summary: Heuristic Methods for Minimizing Cut Bars and Using Leftovers from the One-dimensional Cutting Process
License: MIT
Author: Matheus Pimenta
Author-email: matheus.pimenta@outlook.com
Requires-Python: >=3.11,<4.0
Classifier: Development Status :: 5 - Production/Stable
Classifier: Intended Audience :: Science/Research
Classifier: License :: OSI Approved :: MIT License
Classifier: Natural Language :: English
Classifier: Programming Language :: Python :: 3
Classifier: Programming Language :: Python :: 3.11
Classifier: Programming Language :: Python :: 3.12
Classifier: Topic :: Scientific/Engineering :: Mathematics
Requires-Dist: rich (>=13.7.1,<14.0.0)
Requires-Dist: typer (>=0.9.0,<0.10.0)
Project-URL: Bug Tracker, https://github.com/omatheuspimenta/heuristictree/issues
Project-URL: Code, https://github.com/omatheuspimenta/heuristictree
